agentic_python_coder/__init__.py
agentic_python_coder/agent.py
agentic_python_coder/cli.py
agentic_python_coder/kernel.py
agentic_python_coder/llm.py
agentic_python_coder/mcp_server.py
agentic_python_coder/project_md.py
agentic_python_coder/runner.py
agentic_python_coder/tools.py
agentic_python_coder/examples/__init__.py
agentic_python_coder/examples/clingo/README.md
agentic_python_coder/examples/clingo/clingo.md
agentic_python_coder/examples/clingo/sample_tasks/bird_reasoning.md
agentic_python_coder/examples/clingo/sample_tasks/diagnosis.md
agentic_python_coder/examples/clingo/sample_tasks/simple_coloring.md
agentic_python_coder/examples/clingo/sample_tasks/stable_marriage.md
agentic_python_coder/examples/clingo/sample_tasks/sudoku_mini.md
agentic_python_coder/examples/cpmpy/README.md
agentic_python_coder/examples/cpmpy/cpmpy.md
agentic_python_coder/examples/cpmpy/sample_tasks/magic_square.md
agentic_python_coder/examples/cpmpy/sample_tasks/n_queens.md
agentic_python_coder/examples/regex/README.md
agentic_python_coder/examples/regex/regex.md
agentic_python_coder/examples/regex/sample_tasks/email_extraction.md
agentic_python_coder/examples/regex/sample_tasks/phone_validation.md
agentic_python_coder/examples/regex/sample_tasks/url_parsing.md
agentic_python_coder/models/deepseek31.json
agentic_python_coder/models/gemini25.json
agentic_python_coder/models/gemini3pro.json
agentic_python_coder/models/gpt52.json
agentic_python_coder/models/grok41.json
agentic_python_coder/models/opus45.json
agentic_python_coder/models/qwen3.json
agentic_python_coder/models/sonnet45.json
agentic_python_coder/prompts/system.md
agentic_python_coder/prompts/system_todo.md
agentic_python_coder-3.0.0.dist-info/METADATA
agentic_python_coder-3.0.0.dist-info/WHEEL
agentic_python_coder-3.0.0.dist-info/entry_points.txt
agentic_python_coder-3.0.0.dist-info/licenses/LICENSE
agentic_python_coder-3.0.0.dist-info/RECORD
