Metadata-Version: 2.4
Name: agentic-python-coder
Version: 3.0.0
Summary: A lightweight Python coding agent that writes, executes, and iterates on code through natural language instructions
Author: Stefan Szeider
License: Apache-2.0
License-File: LICENSE
Keywords: agent,ai,automation,code-generation,coding,llm
Classifier: Development Status :: 5 - Production/Stable
Classifier: Intended Audience :: Developers
Classifier: License :: OSI Approved :: Apache Software License
Classifier: Programming Language :: Python :: 3
Classifier: Programming Language :: Python :: 3.13
Classifier: Topic :: Scientific/Engineering :: Artificial Intelligence
Classifier: Topic :: Software Development :: Code Generators
Requires-Python: <3.14,>=3.13
Requires-Dist: ipykernel>=7.1.0
Requires-Dist: jupyter-client>=8.8.0
Requires-Dist: mcp>=1.26.0
Requires-Dist: openai>=2.16.0
Requires-Dist: python-dotenv>=1.2.1
Requires-Dist: pyyaml>=6.0.3
Requires-Dist: rich>=14.3.1
Provides-Extra: dev
Requires-Dist: mypy>=1.19.1; extra == 'dev'
Requires-Dist: ruff>=0.14.14; extra == 'dev'
Provides-Extra: test
Requires-Dist: pytest-asyncio>=1.3.0; extra == 'test'
Requires-Dist: pytest-cov>=7.0.0; extra == 'test'
Requires-Dist: pytest-watch>=4.2.0; extra == 'test'
Requires-Dist: pytest>=9.0.2; extra == 'test'
